  0           0 RESUME                   0

  1           2 LOAD_CONST               0 (0)
              4 LOAD_CONST               1 (None)
              6 IMPORT_NAME              0 (asyncio)
              8 STORE_NAME               0 (asyncio)

  3          10 PUSH_NULL
             12 LOAD_BUILD_CLASS
             14 LOAD_CONST               2 (<code object AIter at 0x0000025F9BB7B830, file "test\async.py", line 3>)
             16 MAKE_FUNCTION            0
             18 LOAD_CONST               3 ('AIter')
             20 PRECALL                  2
             24 CALL                     2
             34 STORE_NAME               1 (AIter)

 18          36 PUSH_NULL
             38 LOAD_BUILD_CLASS
             40 LOAD_CONST               4 (<code object ACtxMgr at 0x0000025F9BB7BC90, file "test\async.py", line 18>)
             42 MAKE_FUNCTION            0
             44 LOAD_CONST               5 ('ACtxMgr')
             46 PRECALL                  2
             50 CALL                     2
             60 STORE_NAME               2 (ACtxMgr)

 28          62 LOAD_CONST               6 (<code object foo at 0x0000025F9BB7BAD0, file "test\async.py", line 28>)
             64 MAKE_FUNCTION            0
             66 STORE_NAME               3 (foo)

 32          68 LOAD_CONST               7 (<code object bar at 0x0000025F9BB81B80, file "test\async.py", line 32>)
             70 MAKE_FUNCTION            0
             72 STORE_NAME               4 (bar)

 37          74 LOAD_CONST               8 (<code object main at 0x0000025F9B7678E0, file "test\async.py", line 37>)
             76 MAKE_FUNCTION            0
             78 STORE_NAME               5 (main)

 48          80 PUSH_NULL
             82 LOAD_NAME                0 (asyncio)
             84 LOAD_ATTR                6 (run)
             94 PUSH_NULL
             96 LOAD_NAME                5 (main)
             98 PRECALL                  0
            102 CALL                     0
            112 PRECALL                  1
            116 CALL                     1
            126 POP_TOP
            128 LOAD_CONST               1 (None)
            130 RETURN_VALUE

Disassembly of <code object AIter at 0x0000025F9BB7B830, file "test\async.py", line 3>:
  3           0 RESUME                   0
              2 LOAD_NAME                0 (__name__)
              4 STORE_NAME               1 (__module__)
              6 LOAD_CONST               0 ('AIter')
              8 STORE_NAME               2 (__qualname__)

  4          10 LOAD_CONST               1 ('ls')
             12 LOAD_NAME                3 (list)
             14 BUILD_TUPLE              2
             16 LOAD_CONST               2 (<code object __init__ at 0x0000025F9BAEEB10, file "test\async.py", line 4>)
             18 MAKE_FUNCTION            4 (annotations)
             20 STORE_NAME               4 (__init__)

  8          22 LOAD_CONST               3 (<code object __aiter__ at 0x0000025F9BD40DB0, file "test\async.py", line 8>)
             24 MAKE_FUNCTION            0
             26 STORE_NAME               5 (__aiter__)

 11          28 LOAD_CONST               4 (<code object __anext__ at 0x0000025F9B9A3C90, file "test\async.py", line 11>)
             30 MAKE_FUNCTION            0
             32 STORE_NAME               6 (__anext__)
             34 LOAD_CONST               5 (None)
             36 RETURN_VALUE

Disassembly of <code object __init__ at 0x0000025F9BAEEB10, file "test\async.py", line 4>:
  4           0 RESUME                   0

  5           2 LOAD_FAST                1 (ls)
              4 LOAD_FAST                0 (self)
              6 STORE_ATTR               0 (ls)

  6          16 LOAD_CONST               1 (0)
             18 LOAD_FAST                0 (self)
             20 STORE_ATTR               1 (index)
             30 LOAD_CONST               0 (None)
             32 RETURN_VALUE

Disassembly of <code object __aiter__ at 0x0000025F9BD40DB0, file "test\async.py", line 8>:
  8           0 RESUME                   0

  9           2 LOAD_FAST                0 (self)
              4 RETURN_VALUE

Disassembly of <code object __anext__ at 0x0000025F9B9A3C90, file "test\async.py", line 11>:
 11           0 RETURN_GENERATOR
              2 POP_TOP
              4 RESUME                   0

 12           6 LOAD_FAST                0 (self)
              8 LOAD_ATTR                0 (index)
             18 LOAD_GLOBAL              3 (NULL + len)
             30 LOAD_FAST                0 (self)
             32 LOAD_ATTR                2 (ls)
             42 PRECALL                  1
             46 CALL                     1
             56 COMPARE_OP               0 (<)
             62 POP_JUMP_FORWARD_IF_FALSE    36 (to 136)

 13          64 LOAD_FAST                0 (self)
             66 LOAD_ATTR                2 (ls)
             76 LOAD_FAST                0 (self)
             78 LOAD_ATTR                0 (index)
             88 BINARY_SUBSCR
             98 STORE_FAST               1 (i)

 14         100 LOAD_FAST                0 (self)
            102 COPY                     1
            104 LOAD_ATTR                0 (index)
            114 LOAD_CONST               1 (1)
            116 BINARY_OP               13 (+=)
            120 SWAP                     2
            122 STORE_ATTR               0 (index)

 15         132 LOAD_FAST                1 (i)
            134 RETURN_VALUE

 16     >>  136 LOAD_GLOBAL              6 (StopAsyncIteration)
            148 RAISE_VARARGS            1

Disassembly of <code object ACtxMgr at 0x0000025F9BB7BC90, file "test\async.py", line 18>:
 18           0 RESUME                   0
              2 LOAD_NAME                0 (__name__)
              4 STORE_NAME               1 (__module__)
              6 LOAD_CONST               0 ('ACtxMgr')
              8 STORE_NAME               2 (__qualname__)

 19          10 LOAD_CONST               1 (<code object __init__ at 0x0000025F9BD403F0, file "test\async.py", line 19>)
             12 MAKE_FUNCTION            0
             14 STORE_NAME               3 (__init__)

 22          16 LOAD_CONST               2 (<code object __aenter__ at 0x0000025F9BB7BD70, file "test\async.py", line 22>)
             18 MAKE_FUNCTION            0
             20 STORE_NAME               4 (__aenter__)

 25          22 LOAD_CONST               3 (<code object __aexit__ at 0x0000025F9BB7BE50, file "test\async.py", line 25>)
             24 MAKE_FUNCTION            0
             26 STORE_NAME               5 (__aexit__)
             28 LOAD_CONST               4 (None)
             30 RETURN_VALUE

Disassembly of <code object __init__ at 0x0000025F9BD403F0, file "test\async.py", line 19>:
 19           0 RESUME                   0

 20           2 LOAD_CONST               0 (None)
              4 RETURN_VALUE

Disassembly of <code object __aenter__ at 0x0000025F9BB7BD70, file "test\async.py", line 22>:
 22           0 RETURN_GENERATOR
              2 POP_TOP
              4 RESUME                   0

 23           6 LOAD_GLOBAL              1 (NULL + print)
             18 LOAD_CONST               1 ('Entering')
             20 PRECALL                  1
             24 CALL                     1
             34 POP_TOP
             36 LOAD_CONST               0 (None)
             38 RETURN_VALUE

Disassembly of <code object __aexit__ at 0x0000025F9BB7BE50, file "test\async.py", line 25>:
 25           0 RETURN_GENERATOR
              2 POP_TOP
              4 RESUME                   0

 26           6 LOAD_GLOBAL              1 (NULL + print)
             18 LOAD_CONST               1 ('Exiting')
             20 PRECALL                  1
             24 CALL                     1
             34 POP_TOP
             36 LOAD_CONST               0 (None)
             38 RETURN_VALUE

Disassembly of <code object foo at 0x0000025F9BB7BAD0, file "test\async.py", line 28>:
 28           0 RETURN_GENERATOR
              2 POP_TOP
              4 RESUME                   0

 29           6 LOAD_GLOBAL              1 (NULL + print)
             18 LOAD_CONST               1 ('This is foo')
             20 PRECALL                  1
             24 CALL                     1
             34 POP_TOP

 30          36 LOAD_CONST               2 (42)
             38 RETURN_VALUE

Disassembly of <code object bar at 0x0000025F9BB81B80, file "test\async.py", line 32>:
 32           0 RETURN_GENERATOR
              2 POP_TOP
              4 RESUME                   0

 33           6 LOAD_GLOBAL              1 (NULL + print)
             18 LOAD_GLOBAL              3 (NULL + foo)
             30 PRECALL                  0
             34 CALL                     0
             44 GET_AWAITABLE            0
             46 LOAD_CONST               0 (None)
        >>   48 SEND                     3 (to 56)
             50 YIELD_VALUE
             52 RESUME                   3
             54 JUMP_BACKWARD_NO_INTERRUPT     4 (to 48)
        >>   56 PRECALL                  1
             60 CALL                     1
             70 POP_TOP

 34          72 LOAD_GLOBAL              1 (NULL + print)
             84 LOAD_CONST               1 ('This is bar')
             86 PRECALL                  1
             90 CALL                     1
            100 POP_TOP

 35         102 LOAD_CONST               2 ('bar end')
            104 RETURN_VALUE

Disassembly of <code object main at 0x0000025F9B7678E0, file "test\async.py", line 37>:
 37           0 RETURN_GENERATOR
              2 POP_TOP
              4 RESUME                   0

 38           6 LOAD_GLOBAL              1 (NULL + print)
             18 LOAD_GLOBAL              3 (NULL + bar)
             30 PRECALL                  0
             34 CALL                     0
             44 GET_AWAITABLE            0
             46 LOAD_CONST               0 (None)
        >>   48 SEND                     3 (to 56)
             50 YIELD_VALUE
             52 RESUME                   3
             54 JUMP_BACKWARD_NO_INTERRUPT     4 (to 48)
        >>   56 PRECALL                  1
             60 CALL                     1
             70 POP_TOP

 39          72 LOAD_GLOBAL              5 (NULL + AIter)
             84 BUILD_LIST               0
             86 LOAD_CONST               1 (((1, 'a'), (2, 'b'), (3, 'c')))
             88 LIST_EXTEND              1
             90 PRECALL                  1
             94 CALL                     1
            104 STORE_FAST               0 (a)

 40         106 LOAD_FAST                0 (a)
            108 GET_AITER
        >>  110 GET_ANEXT
            112 LOAD_CONST               0 (None)
        >>  114 SEND                     3 (to 122)
            116 YIELD_VALUE
            118 RESUME                   3
            120 JUMP_BACKWARD_NO_INTERRUPT     4 (to 114)
        >>  122 UNPACK_SEQUENCE          2
            126 STORE_FAST               1 (idx)
            128 STORE_FAST               2 (item)

 41         130 LOAD_GLOBAL              1 (NULL + print)
            142 LOAD_FAST                1 (idx)
            144 LOAD_FAST                2 (item)
            146 PRECALL                  2
            150 CALL                     2
            160 POP_TOP
            162 JUMP_BACKWARD           27 (to 110)

 40     >>  164 END_ASYNC_FOR

 43         166 LOAD_GLOBAL              7 (NULL + ACtxMgr)
            178 PRECALL                  0
            182 CALL                     0
            192 BEFORE_ASYNC_WITH
            194 GET_AWAITABLE            1
            196 LOAD_CONST               0 (None)
        >>  198 SEND                     3 (to 206)
            200 YIELD_VALUE
            202 RESUME                   3
            204 JUMP_BACKWARD_NO_INTERRUPT     4 (to 198)
        >>  206 STORE_FAST               0 (a)

 44         208 LOAD_GLOBAL              1 (NULL + print)
            220 LOAD_CONST               2 ('In context manager')
            222 PRECALL                  1
            226 CALL                     1
            236 POP_TOP

 43         238 LOAD_CONST               0 (None)
            240 LOAD_CONST               0 (None)
            242 LOAD_CONST               0 (None)
            244 PRECALL                  2
            248 CALL                     2
            258 GET_AWAITABLE            2
            260 LOAD_CONST               0 (None)
        >>  262 SEND                     3 (to 270)
            264 YIELD_VALUE
            266 RESUME                   3
            268 JUMP_BACKWARD_NO_INTERRUPT     4 (to 262)
        >>  270 POP_TOP
            272 JUMP_FORWARD            17 (to 308)
        >>  274 PUSH_EXC_INFO
            276 WITH_EXCEPT_START
            278 GET_AWAITABLE            2
            280 LOAD_CONST               0 (None)
        >>  282 SEND                     3 (to 290)
            284 YIELD_VALUE
            286 RESUME                   3
            288 JUMP_BACKWARD_NO_INTERRUPT     4 (to 282)
        >>  290 POP_JUMP_FORWARD_IF_TRUE     4 (to 300)
            292 RERAISE                  2
        >>  294 COPY                     3
            296 POP_EXCEPT
            298 RERAISE                  1
        >>  300 POP_TOP
            302 POP_EXCEPT
            304 POP_TOP
            306 POP_TOP

 46     >>  308 LOAD_GLOBAL              1 (NULL + print)
            320 LOAD_CONST               3 ('Main end')
            322 PRECALL                  1
            326 CALL                     1
            336 POP_TOP
            338 LOAD_CONST               0 (None)
            340 RETURN_VALUE
ExceptionTable:
  110 to 120 -> 164 [1]
  206 to 236 -> 274 [1] lasti
  274 to 292 -> 294 [3] lasti
  300 to 300 -> 294 [3] lasti
