  0           0 RESUME                   0

  1           2 BUILD_LIST               0
              4 LOAD_CONST               0 ((1, 'hello', 114.514))
              6 LIST_EXTEND              1
              8 STORE_NAME               0 (a)

  2          10 LOAD_CONST               1 (1)
             12 LOAD_NAME                0 (a)
             14 LOAD_CONST               2 ('world')
             16 BUILD_TUPLE              3
             18 STORE_NAME               1 (b)

  3          20 LOAD_CONST               1 (1)
             22 LOAD_CONST               3 (b'bb')
             24 LOAD_CONST               4 ('ccc')
             26 LOAD_NAME                2 (print)
             28 LOAD_CONST               5 ((1, 'b', 'c', 'p'))
             30 BUILD_CONST_KEY_MAP      4
             32 STORE_NAME               3 (c)

  4          34 LOAD_CONST               6 (111)
             36 STORE_NAME               4 (key)

  5          38 LOAD_NAME                4 (key)
             40 LOAD_CONST               7 (97)
             42 LOAD_CONST               8 ('b')
             44 LOAD_CONST               9 (None)
             46 BUILD_MAP                2
             48 STORE_NAME               5 (d)

  6          50 LOAD_CONST              10 (1232)
             52 LOAD_CONST              11 (0)
             54 LOAD_CONST               9 (None)
             56 LOAD_NAME                2 (print)
             58 BUILD_SET                4
             60 STORE_NAME               6 (e)

  7          62 PUSH_NULL
             64 LOAD_NAME                3 (c)
             66 LOAD_METHOD              7 (get)
             88 LOAD_CONST              12 ('p')
             90 PRECALL                  1
             94 CALL                     1
            104 LOAD_NAME                0 (a)
            106 LOAD_NAME                1 (b)
            108 LOAD_NAME                3 (c)
            110 LOAD_NAME                5 (d)
            112 PRECALL                  4
            116 CALL                     4
            126 POP_TOP
            128 LOAD_CONST               9 (None)
            130 RETURN_VALUE
