  0           0 RESUME                   0

  1           2 BUILD_LIST               0
              4 LOAD_CONST               0 ((1, 3, 5, 7, 9))
              6 LIST_EXTEND              1
              8 STORE_NAME               0 (arr)

  2          10 PUSH_NULL
             12 LOAD_NAME                1 (enumerate)
             14 LOAD_NAME                0 (arr)
             16 PRECALL                  1
             20 CALL                     1
             30 GET_ITER
        >>   32 FOR_ITER                40 (to 114)
             34 UNPACK_SEQUENCE          2
             38 STORE_NAME               2 (i)
             40 STORE_NAME               3 (v)

  3          42 LOAD_NAME                2 (i)
             44 LOAD_CONST               1 (1)
             46 BINARY_OP                0 (+)
             50 STORE_NAME               4 (line)

  4          52 LOAD_NAME                4 (line)
             54 LOAD_CONST               2 (2)
             56 BINARY_OP                6 (%)
             60 LOAD_CONST               3 (0)
             62 COMPARE_OP               2 (==)
             68 POP_JUMP_FORWARD_IF_FALSE     1 (to 72)

  5          70 JUMP_BACKWARD           20 (to 32)

  6     >>   72 LOAD_NAME                4 (line)
             74 LOAD_CONST               4 (3)
             76 COMPARE_OP               2 (==)
             82 POP_JUMP_FORWARD_IF_FALSE     2 (to 88)

  7          84 POP_TOP
             86 JUMP_FORWARD            13 (to 114)

  8     >>   88 PUSH_NULL
             90 LOAD_NAME                5 (print)
             92 LOAD_NAME                4 (line)
             94 LOAD_NAME                3 (v)
             96 PRECALL                  2
            100 CALL                     2
            110 POP_TOP
            112 JUMP_BACKWARD           41 (to 32)

 10     >>  114 PUSH_NULL
            116 LOAD_NAME                5 (print)
            118 LOAD_CONST               5 ('end')
            120 PRECALL                  1
            124 CALL                     1
            134 POP_TOP

 11         136 PUSH_NULL
            138 LOAD_NAME                5 (print)
            140 LOAD_CONST               6 ('Test')
            142 PRECALL                  1
            146 CALL                     1
            156 POP_TOP
            158 LOAD_CONST               7 (None)
            160 RETURN_VALUE
