  0           0 RESUME                   0

  1           2 LOAD_CONST               0 (0)
              4 LOAD_CONST               1 (None)
              6 IMPORT_NAME              0 (sys)
              8 STORE_NAME               0 (sys)

  2          10 LOAD_CONST               0 (0)
             12 LOAD_CONST               2 (('*',))
             14 IMPORT_NAME              1 (pwn)
             16 IMPORT_STAR

  3          18 LOAD_CONST               0 (0)
             20 LOAD_CONST               1 (None)
             22 IMPORT_NAME              2 (numpy)
             24 STORE_NAME               3 (np)

  4          26 LOAD_CONST               0 (0)
             28 LOAD_CONST               1 (None)
             30 IMPORT_NAME              4 (matplotlib.pyplot)
             32 IMPORT_FROM              5 (pyplot)
             34 STORE_NAME               6 (plt)
             36 POP_TOP

  5          38 LOAD_CONST               0 (0)
             40 LOAD_CONST               3 (('popen', 'system'))
             42 IMPORT_NAME              7 (os)
             44 IMPORT_FROM              8 (popen)
             46 STORE_NAME               9 (p)
             48 IMPORT_FROM             10 (system)
             50 STORE_NAME              10 (system)
             52 POP_TOP
             54 LOAD_CONST               1 (None)
             56 RETURN_VALUE
